{
  "id": "1427701",
  "name": "sd",
  "font_family": "iconfont",
  "css_prefix_text": "icon-",
  "description": "",
  "glyphs": [
    {
      "icon_id": "156575",
      "name": "优惠券",
      "font_class": "youhuiquan",
      "unicode": "e625",
      "unicode_decimal": 58917
    },
    {
      "icon_id": "252743",
      "name": "购物车",
      "font_class": "gouwuche",
      "unicode": "e726",
      "unicode_decimal": 59174
    },
    {
      "icon_id": "396563",
      "name": "向上箭头",
      "font_class": "xiangshangjiantou",
      "unicode": "e613",
      "unicode_decimal": 58899
    },
    {
      "icon_id": "411545",
      "name": "分享",
      "font_class": "fenxiang",
      "unicode": "e627",
      "unicode_decimal": 58919
    },
    {
      "icon_id": "430708",
      "name": "向右箭头",
      "font_class": "xiangyoujiantou",
      "unicode": "e662",
      "unicode_decimal": 58978
    },
    {
      "icon_id": "438591",
      "name": "3 反馈意见 白",
      "font_class": "3fankuiyijianbai",
      "unicode": "e85a",
      "unicode_decimal": 59482
    },
    {
      "icon_id": "554451",
      "name": "向下箭头",
      "font_class": "iconset0417",
      "unicode": "e728",
      "unicode_decimal": 59176
    },
    {
      "icon_id": "554453",
      "name": "向左箭头",
      "font_class": "iconset0419",
      "unicode": "e72a",
      "unicode_decimal": 59178
    },
    {
      "icon_id": "554454",
      "name": "向右箭头",
      "font_class": "iconset0420",
      "unicode": "e72b",
      "unicode_decimal": 59179
    },
    {
      "icon_id": "586300",
      "name": "五角星",
      "font_class": "star",
      "unicode": "e61b",
      "unicode_decimal": 58907
    },
    {
      "icon_id": "637478",
      "name": "分享",
      "font_class": "fenxiang1",
      "unicode": "e69a",
      "unicode_decimal": 59034
    },
    {
      "icon_id": "691112",
      "name": "回到顶部",
      "font_class": "huidaodingbu",
      "unicode": "e631",
      "unicode_decimal": 58929
    },
    {
      "icon_id": "700837",
      "name": "客服",
      "font_class": "kefu",
      "unicode": "e646",
      "unicode_decimal": 58950
    },
    {
      "icon_id": "720827",
      "name": "我的消息icon",
      "font_class": "wodexiaoxiicon",
      "unicode": "e65f",
      "unicode_decimal": 58975
    },
    {
      "icon_id": "720969",
      "name": "关注",
      "font_class": "xiazai11",
      "unicode": "e60b",
      "unicode_decimal": 58891
    },
    {
      "icon_id": "795507",
      "name": "收藏",
      "font_class": "ai-mark",
      "unicode": "e667",
      "unicode_decimal": 58983
    },
    {
      "icon_id": "869367",
      "name": "客服",
      "font_class": "kefu1",
      "unicode": "e63a",
      "unicode_decimal": 58938
    },
    {
      "icon_id": "886701",
      "name": "关注",
      "font_class": "guanzhu",
      "unicode": "e614",
      "unicode_decimal": 58900
    },
    {
      "icon_id": "897810",
      "name": "会员",
      "font_class": "huiyuan",
      "unicode": "e641",
      "unicode_decimal": 58945
    },
    {
      "icon_id": "978987",
      "name": "反馈意见",
      "font_class": "fankuiyijian",
      "unicode": "e649",
      "unicode_decimal": 58953
    },
    {
      "icon_id": "1016681",
      "name": "店铺",
      "font_class": "dianpu",
      "unicode": "e638",
      "unicode_decimal": 58936
    },
    {
      "icon_id": "1036406",
      "name": "会员",
      "font_class": "shouye",
      "unicode": "e606",
      "unicode_decimal": 58886
    },
    {
      "icon_id": "1069397",
      "name": "优惠券",
      "font_class": "youhuiquan1",
      "unicode": "e645",
      "unicode_decimal": 58949
    },
    {
      "icon_id": "1110425",
      "name": "向左箭头",
      "font_class": "xiangzuojiantou",
      "unicode": "e617",
      "unicode_decimal": 58903
    },
    {
      "icon_id": "1211275",
      "name": "购物车",
      "font_class": "gouwuche1",
      "unicode": "e618",
      "unicode_decimal": 58904
    },
    {
      "icon_id": "1252045",
      "name": "优惠券",
      "font_class": "youhuiquan2",
      "unicode": "e69f",
      "unicode_decimal": 59039
    },
    {
      "icon_id": "1314422",
      "name": "向上箭头",
      "font_class": "xiangshangjiantou1",
      "unicode": "e608",
      "unicode_decimal": 58888
    },
    {
      "icon_id": "1638194",
      "name": "店铺",
      "font_class": "dianpu1",
      "unicode": "e60c",
      "unicode_decimal": 58892
    },
    {
      "icon_id": "1718086",
      "name": "991菜单_五角星（满）",
      "font_class": "caidan_wujiaoxingman",
      "unicode": "e6b4",
      "unicode_decimal": 59060
    },
    {
      "icon_id": "1901672",
      "name": "关注",
      "font_class": "guanzhu1",
      "unicode": "e600",
      "unicode_decimal": 58880
    },
    {
      "icon_id": "2076253",
      "name": "回到顶部",
      "font_class": "huidaodingbu1",
      "unicode": "e88d",
      "unicode_decimal": 59533
    },
    {
      "icon_id": "2077822",
      "name": "搜索",
      "font_class": "sousuo",
      "unicode": "e64a",
      "unicode_decimal": 58954
    },
    {
      "icon_id": "4449451",
      "name": "搜索",
      "font_class": "sousuo1",
      "unicode": "e65b",
      "unicode_decimal": 58971
    },
    {
      "icon_id": "4640893",
      "name": "分享",
      "font_class": "fenxiang2",
      "unicode": "e615",
      "unicode_decimal": 58901
    },
    {
      "icon_id": "4811074",
      "name": "购物车",
      "font_class": "tubiaozhizuomoban",
      "unicode": "e607",
      "unicode_decimal": 58887
    },
    {
      "icon_id": "5121492",
      "name": "二维码",
      "font_class": "erweima",
      "unicode": "e63c",
      "unicode_decimal": 58940
    },
    {
      "icon_id": "5288593",
      "name": "收藏",
      "font_class": "shoucang",
      "unicode": "e66f",
      "unicode_decimal": 58991
    },
    {
      "icon_id": "5288601",
      "name": "向下箭头",
      "font_class": "xiangxiajiantou",
      "unicode": "e673",
      "unicode_decimal": 58995
    },
    {
      "icon_id": "5643526",
      "name": "收藏",
      "font_class": "shoucang1",
      "unicode": "e609",
      "unicode_decimal": 58889
    },
    {
      "icon_id": "7134737",
      "name": "收藏",
      "font_class": "shoucang2",
      "unicode": "e67e",
      "unicode_decimal": 59006
    },
    {
      "icon_id": "7148752",
      "name": "我的消息",
      "font_class": "wodexiaoxi",
      "unicode": "e647",
      "unicode_decimal": 58951
    },
    {
      "icon_id": "8102707",
      "name": "客服",
      "font_class": "icon-test",
      "unicode": "e60a",
      "unicode_decimal": 58890
    },
    {
      "icon_id": "8361765",
      "name": "二维码",
      "font_class": "erweima1",
      "unicode": "e6bd",
      "unicode_decimal": 59069
    },
    {
      "icon_id": "8820134",
      "name": "关注",
      "font_class": "guanzhu2",
      "unicode": "e6c4",
      "unicode_decimal": 59076
    },
    {
      "icon_id": "10156378",
      "name": "搜索",
      "font_class": "sousuo2",
      "unicode": "e651",
      "unicode_decimal": 58961
    },
    {
      "icon_id": "10232751",
      "name": "购物车",
      "font_class": "gouwuche2",
      "unicode": "e78b",
      "unicode_decimal": 59275
    }
  ]
}
